{"v":4,"entries":{"actions--add":{"type":"story","id":"actions--add","name":"Add","title":"Actions","importPath":"./stories/actions/actions.stories.tsx","tags":["story"]},"actions--remove":{"type":"story","id":"actions--remove","name":"Remove","title":"Actions","importPath":"./stories/actions/actions.stories.tsx","tags":["story"]},"actions--update":{"type":"story","id":"actions--update","name":"Update","title":"Actions","importPath":"./stories/actions/actions.stories.tsx","tags":["story"]},"actions--mode":{"type":"story","id":"actions--mode","name":"Mode","title":"Actions","importPath":"./stories/actions/actions.stories.tsx","tags":["story"]},"actions--initial":{"type":"story","id":"actions--initial","name":"Initial","title":"Actions","importPath":"./stories/actions/initial.stories.tsx","tags":["story"]},"actions--with-default-style":{"type":"story","id":"actions--with-default-style","name":"With Default Style","title":"Actions","importPath":"./stories/actions/initial.stories.tsx","tags":["story"]},"box--docs":{"id":"box--docs","title":"Box","name":"Docs","importPath":"./stories/box.stories.tsx","type":"docs","tags":["autodocs","docs"],"storiesImports":[]},"box--control":{"type":"story","id":"box--control","name":"Control","title":"Box","importPath":"./stories/box.stories.tsx","tags":["autodocs","story"]},"box--with-only-style":{"type":"story","id":"box--with-only-style","name":"With Only Style","title":"Box","importPath":"./stories/box.stories.tsx","tags":["autodocs","story"]},"box--with-only-classname":{"type":"story","id":"box--with-only-classname","name":"With Only Classname","title":"Box","importPath":"./stories/box.stories.tsx","tags":["autodocs","story"]}}}
